capblood_seq_viz/__init__.py
capblood_seq_viz/launch.py
capblood_seq_viz/server.py
capblood_seq_viz/assets/__init__.py
capblood_seq_viz/assets/blood_logo.png
capblood_seq_viz/assets/favicon.ico
capblood_seq_viz/common/__init__.py
capblood_seq_viz/common/data.py
capblood_seq_viz/common/resources.py
capblood_seq_viz/config/__init__.py
capblood_seq_viz/config/config.py
capblood_seq_viz/config/default.json
capblood_seq_viz/data/__init__.py
capblood_seq_viz/data/cell_counts.py
capblood_seq_viz/data/diurnality.py
capblood_seq_viz/data/individuality.py
capblood_seq_viz/data/pathways.py
capblood_seq_viz/data/tSNE.py
capblood_seq_viz/figures/__init__.py
capblood_seq_viz/figures/diurnality.py
capblood_seq_viz/figures/individuality.py
capblood_seq_viz/figures/summary.py
capblood_seq_viz/functions/__init__.py
capblood_seq_viz/functions/diurnality.py
capblood_seq_viz/functions/index.py
capblood_seq_viz/functions/individuality.py
capblood_seq_viz/functions/summary.py
capblood_seq_viz/layouts/__init__.py
capblood_seq_viz/layouts/about.py
capblood_seq_viz/layouts/diurnality.py
capblood_seq_viz/layouts/index.py
capblood_seq_viz/layouts/individuality.py
capblood_seq_viz/layouts/summary.py
capblood_seq_viz-0.2.2.dist-info/DESCRIPTION.rst
capblood_seq_viz-0.2.2.dist-info/METADATA
capblood_seq_viz-0.2.2.dist-info/RECORD
capblood_seq_viz-0.2.2.dist-info/WHEEL
capblood_seq_viz-0.2.2.dist-info/entry_points.txt
capblood_seq_viz-0.2.2.dist-info/metadata.json
capblood_seq_viz-0.2.2.dist-info/top_level.txt
