Metadata-Version: 2.0
Name: capblood-seq-viz
Version: 0.2.2
Summary: Interactive visualization web app for capillary blood data
Home-page: https://github.com/ThomsonLab/capblood-seq-viz
Author: David Brown
Author-email: dibidave@gmail.com
License: MIT
Platform: UNKNOWN
Requires-Python: ~=3.6
Requires-Dist: capblood-seq (>=0.2.2)
Requires-Dist: gunicorn (<21,>=20.0.4)
Requires-Dist: dash (>=1.9.1)
Requires-Dist: dash-core-components (>=1.8.1)
Requires-Dist: dash-html-components (>=1.0.2)
Requires-Dist: dash-renderer (>=1.2.4)
Requires-Dist: dash-bootstrap-components (>=0.9.1)
Requires-Dist: dash-table (>=4.6.1)
Requires-Dist: plotly
Requires-Dist: flask
Requires-Dist: importlib-resources (>=1.4.0)
Requires-Dist: pandas
Requires-Dist: numpy
Requires-Dist: bioservices
